pyndjs/__init__.py
pyndjs/pyndjs.py
pyndjs-1.0.0.dist-info/METADATA
pyndjs-1.0.0.dist-info/WHEEL
pyndjs-1.0.0.dist-info/top_level.txt
pyndjs-1.0.0.dist-info/RECORD
